MANIFEST.in
README.txt
setup.cfg
setup.py
docs/HISTORY.txt
docs/INSTALL.txt
docs/LICENSE.GPL
docs/LICENSE.txt
zopyx/__init__.py
zopyx.tinymceplugins.imgmap.egg-info/PKG-INFO
zopyx.tinymceplugins.imgmap.egg-info/SOURCES.txt
zopyx.tinymceplugins.imgmap.egg-info/dependency_links.txt
zopyx.tinymceplugins.imgmap.egg-info/entry_points.txt
zopyx.tinymceplugins.imgmap.egg-info/namespace_packages.txt
zopyx.tinymceplugins.imgmap.egg-info/not-zip-safe
zopyx.tinymceplugins.imgmap.egg-info/paster_plugins.txt
zopyx.tinymceplugins.imgmap.egg-info/requires.txt
zopyx.tinymceplugins.imgmap.egg-info/top_level.txt
zopyx/tinymceplugins/__init__.py
zopyx/tinymceplugins/imgmap/__init__.py
zopyx/tinymceplugins/imgmap/configure.zcml
zopyx/tinymceplugins/imgmap/profiles.zcml
zopyx/tinymceplugins/imgmap/setuphandlers.py
zopyx/tinymceplugins/imgmap/skins.zcml
zopyx/tinymceplugins/imgmap/tests.py
zopyx/tinymceplugins/imgmap/version.txt
zopyx/tinymceplugins/imgmap/browser/__init__.py
zopyx/tinymceplugins/imgmap/browser/configure.zcml
zopyx/tinymceplugins/imgmap/browser/document.py
zopyx/tinymceplugins/imgmap/browser/document_anchors.pt
zopyx/tinymceplugins/imgmap/browser/interfaces.py
zopyx/tinymceplugins/imgmap/browser/viewlet.pt
zopyx/tinymceplugins/imgmap/browser/viewlets.py
zopyx/tinymceplugins/imgmap/browser/images/README.txt
zopyx/tinymceplugins/imgmap/browser/stylesheets/README.txt
zopyx/tinymceplugins/imgmap/browser/stylesheets/main.css
zopyx/tinymceplugins/imgmap/locales/README.txt
zopyx/tinymceplugins/imgmap/profiles/default/metadata.xml
zopyx/tinymceplugins/imgmap/profiles/default/skins.xml
zopyx/tinymceplugins/imgmap/profiles/default/tinymce.xml
zopyx/tinymceplugins/imgmap/profiles/default/zopyx.imgmap_various.txt
zopyx/tinymceplugins/imgmap/skins/zopyx_tinymceplugins_imgmap/imgmap/changelog
zopyx/tinymceplugins/imgmap/skins/zopyx_tinymceplugins_imgmap/imgmap/editor_plugin.js
zopyx/tinymceplugins/imgmap/skins/zopyx_tinymceplugins_imgmap/imgmap/editor_plugin_src.js
zopyx/tinymceplugins/imgmap/skins/zopyx_tinymceplugins_imgmap/imgmap/install.txt
zopyx/tinymceplugins/imgmap/skins/zopyx_tinymceplugins_imgmap/imgmap/license_GPL.txt
zopyx/tinymceplugins/imgmap/skins/zopyx_tinymceplugins_imgmap/imgmap/popup.html.dtml
zopyx/tinymceplugins/imgmap/skins/zopyx_tinymceplugins_imgmap/imgmap/css/imgmap.css
zopyx/tinymceplugins/imgmap/skins/zopyx_tinymceplugins_imgmap/imgmap/images/accept.gif
