Metadata-Version: 1.1
Name: zopyx.tinymceplugins.imgmap
Version: 0.3.2.1
Summary: Imgmap editor plugin for TinyMCE
Home-page: http://svn.plone.org/svn/collective/
Author: Andreas Jung
Author-email: info@zopyx.com
License: GPL
Keywords: Plone Zope TinyMCE editor
Platform: UNKNOWN
Classifier: Framework :: Plone
Classifier: Programming Language :: Python
